{
	"editor": {
		"allAngles": false,
		"entityTextureMode": false
	},
	"textureWidth": 16,
	"textureHeight": 16,
	"textureSizes": {
	},
	"textures": {
		
	},
	"elements": [
		{
			"name": "center",
			"from": [ 1.5, 0.1, 1.5 ],
			"to": [ 8.0, 0.1, 8.0 ],
			"rotationOrigin": [ 1.0, 0.0, 1.0 ],
			"faces": {
				"up": { "texture": "#sauerkraut", "uv": [ 1.0, 1.0, 7.5, 7.5 ] }
			},
			"children": [
				{
					"name": "main",
					"from": [ 4.0, 0.0, 4.0 ],
					"to": [ 9.0, 2.0, 9.0 ],
					"rotationOrigin": [ 4.0, 0.0, 4.0 ],
					"faces": {
						"north": { "texture": "#sauerkraut", "uv": [ 3.5, 5.5, 8.5, 7.5 ] },
						"east": { "texture": "#sauerkraut", "uv": [ 6.0, 7.0, 11.0, 9.0 ] },
						"south": { "texture": "#sauerkraut", "uv": [ 4.5, 7.0, 9.5, 9.0 ] },
						"west": { "texture": "#sauerkraut", "uv": [ 4.5, 7.5, 9.5, 9.5 ] },
						"up": { "texture": "#sauerkraut", "uv": [ 4.0, 4.0, 9.0, 9.0 ] }
					}
				},
				{
					"name": "w",
					"from": [ 0.6, 0.0, 4.0 ],
					"to": [ 4.6, 0.0, 9.0 ],
					"rotationOrigin": [ 0.6, 0.0, 4.0 ],
					"rotationZ": 30.0,
					"faces": {
						"up": { "texture": "#sauerkraut", "uv": [ 1.0, 4.5, 5.0, 9.5 ] }
					}
				},
				{
					"name": "e",
					"from": [ 9.0, 2.0, 4.0 ],
					"to": [ 13.0, 2.0, 9.0 ],
					"rotationOrigin": [ 9.0, 2.0, 4.0 ],
					"rotationZ": -30.0,
					"faces": {
						"up": { "texture": "#sauerkraut", "uv": [ 11.0, 5.0, 15.0, 10.0 ] }
					}
				},
				{
					"name": "s",
					"from": [ 4.0, 2.0, 9.0 ],
					"to": [ 9.0, 2.0, 13.0 ],
					"rotationOrigin": [ 4.0, 2.0, 9.0 ],
					"rotationX": 30.0,
					"faces": {
						"up": { "texture": "#sauerkraut", "uv": [ 5.5, 11.0, 10.5, 15.0 ] }
					}
				},
				{
					"name": "n",
					"from": [ 4.0, 0.0, 0.6 ],
					"to": [ 9.0, 0.0, 4.6 ],
					"rotationOrigin": [ 4.0, 0.0, 0.6 ],
					"rotationX": -30.0,
					"faces": {
						"up": { "texture": "#sauerkraut", "uv": [ 4.5, 0.5, 9.5, 4.5 ] }
					}
				},
				{
					"name": "ne",
					"from": [ 7.1, 2.0, 3.1 ],
					"to": [ 11.1, 2.0, 7.1 ],
					"rotationOrigin": [ 7.1, 2.0, 3.1 ],
					"rotationY": 45.0,
					"rotationZ": -30.0,
					"faces": {
						"up": { "texture": "#sauerkraut", "uv": [ 11.5, 6.0, 15.5, 10.0 ] }
					}
				},
				{
					"name": "se",
					"from": [ 10.1, 2.0, 7.1 ],
					"to": [ 14.1, 2.0, 11.1 ],
					"rotationOrigin": [ 10.1, 2.0, 7.1 ],
					"rotationY": -45.0,
					"rotationZ": -30.0,
					"faces": {
						"up": { "texture": "#sauerkraut", "uv": [ 10.0, 1.5, 14.0, 5.5 ] }
					}
				},
				{
					"name": "nw",
					"from": [ 3.6, 0.0, 0.6 ],
					"to": [ 7.6, 0.0, 4.6 ],
					"rotationOrigin": [ 3.6, 0.0, 0.6 ],
					"rotationY": -45.0,
					"rotationZ": 30.0,
					"faces": {
						"up": { "texture": "#sauerkraut", "uv": [ 2.5, 2.0, 6.5, 6.0 ] }
					}
				},
				{
					"name": "sw",
					"from": [ 0.6, 0.0, 9.6 ],
					"to": [ 4.6, 0.0, 13.6 ],
					"rotationOrigin": [ 0.6, 0.0, 9.6 ],
					"rotationY": 45.0,
					"rotationZ": 30.0,
					"faces": {
						"up": { "texture": "#sauerkraut", "uv": [ 2.0, 9.5, 6.0, 13.5 ] }
					}
				}
			]
		},
		{
			"name": "center2",
			"from": [ 8.0, 0.1, 1.5 ],
			"to": [ 14.5, 0.1, 8.0 ],
			"rotationOrigin": [ 8.0, 0.0, 1.0 ],
			"faces": {
				"up": { "texture": "#sauerkraut", "uv": [ 8.5, 1.0, 15.0, 7.5 ] }
			}
		},
		{
			"name": "center3",
			"from": [ 8.0, 0.1, 8.0 ],
			"to": [ 14.5, 0.1, 14.5 ],
			"rotationOrigin": [ 8.0, 0.0, 8.0 ],
			"faces": {
				"up": { "texture": "#sauerkraut", "uv": [ 8.5, 8.5, 15.0, 15.0 ] }
			}
		},
		{
			"name": "center4",
			"from": [ 1.5, 0.1, 8.0 ],
			"to": [ 8.0, 0.1, 14.5 ],
			"rotationOrigin": [ 1.0, 0.0, 8.0 ],
			"faces": {
				"up": { "texture": "#sauerkraut", "uv": [ 1.0, 8.5, 7.5, 15.0 ] }
			}
		}
	]}